fc_ims.py
fc_lys1-1.post0.dist-info/METADATA
fc_lys1-1.post0.dist-info/WHEEL
fc_lys1-1.post0.dist-info/top_level.txt
fc_lys1-1.post0.dist-info/RECORD
