Metadata-Version: 2.1
Name: fc-lys1
Version: 1-0
Summary: 大数据一班
Home-page: UNKNOWN
Author: UNKNOWN
Author-email: fc@lys1.com
License: UNKNOWN
Platform: UNKNOWN
